bellparallel/__init__.py
bellparallel/utils.py
bellparallel-0.0.5.dist-info/LICENSE
bellparallel-0.0.5.dist-info/METADATA
bellparallel-0.0.5.dist-info/WHEEL
bellparallel-0.0.5.dist-info/top_level.txt
bellparallel-0.0.5.dist-info/RECORD
