Metadata-Version: 2.1
Name: bellparallel
Version: 0.0.5
Summary: Parallel execution utils
Home-page: https://github.com/FabianBell/Packages/tree/master/bellparallel
Author: Fabian Bell
Author-email: fabianx.bell@gmail.com
License: MIT
Platform: UNKNOWN
Classifier: Programming Language :: Python :: 3
Classifier: License :: OSI Approved :: MIT License
